[
    {
        "ranking": "1",
        "title": "Ya Borracho",
        "artist": null,
        "image": "https://lh3.googleusercontent.com/__avYDQt9-lmKRXP7_SxEU5XLjyO__K-UhkxuNcQOe6Pxn-lK4ICIPIriQwtq0vQIAzD1xFyDpxW3T8F=w180-h180-l90-rj",
        "prev": "1",
        "streak": "9",
        "streams": "443,934",
        "youtubeID": "7SsmyjVF1Oo"
    },
    {
        "ranking": "2",
        "title": "Cero Empatía",
        "artist": null,
        "image": "https://lh3.googleusercontent.com/jo2zlBvnIfzzfaV0aPtVJYWTfby7fVfVp3QVGGeVFwAp1-sbncw-mV0xR1wksLHPbESj0NpbthK9D5c=w180-h180-l90-rj",
        "prev": "2",
        "streak": "61",
        "streams": "421,153",
        "youtubeID": "GNyembSi1nw"
    },
    {
        "ranking": "3",
        "title": "Rey Sin Reina",
        "artist": null,
        "image": "https://lh3.googleusercontent.com/fLp6P2WVx8RAcj7ZQPhtdi-v1kwP3PGspWFq4a3qthPDTIi0aD5wQ9H6MJlc_v4BJlw2DU0m9BxBsY6h=w180-h180-l90-rj",
        "prev": "3",
        "streak": "72",
        "streams": "371,946",
        "youtubeID": "ElRVZ09939k"
    },
    {
        "ranking": "4",
        "title": "El Beneficio De La Duda",
        "artist": null,
        "image": "https://lh3.googleusercontent.com/qtmdORuF3VSAEFpmhk8F4Qn4jmQrQl_90iipVPpTp9ay6A3llKb5XUqbdSWgm8baMkvZw3R-U_Ec2E0=w180-h180-l90-rj",
        "prev": "5",
        "streak": "69",
        "streams": "363,036",
        "youtubeID": "iIgsCYgo5P4"
    },
    {
        "ranking": "5",
        "title": "En Privado",
        "artist": null,
        "image": "https://lh3.googleusercontent.com/myLU1dWKKL8xPu1N-pdM1lNChUAxzpWHhaApJY-eTCKwOwLZJ3lVXghue8cXfv3zSWoreGdmivYgpiU=w180-h180-l90-rj",
        "prev": "4",
        "streak": "50",
        "streams": "339,896",
        "youtubeID": "kE1-O0tU-UU"
    },
    {
        "ranking": "6",
        "title": "Al Final del Día",
        "artist": null,
        "image": "https://lh3.googleusercontent.com/EM_hmfkquxgXLAphjOgUFHVT-2LeXnhuG4b604VQpEj1WLreJ6jq3J1RAK3F0HACg1--3j41DUX4uDD_=w180-h180-l90-rj",
        "prev": "-",
        "streak": "1",
        "streams": "339,544",
        "youtubeID": "l9ivRwMrvpc"
    },
    {
        "ranking": "7",
        "title": "El Mayor de los Ranas",
        "artist": null,
        "image": "https://lh3.googleusercontent.com/te1qJ2RUESuGe-8kIiJUSzHaXi2Rr1hYnM4aUwglQad2L-CNM1TykNblBmT3ngf2SenU5Sc4nLmbpgeqZw=w180-h180-l90-rj",
        "prev": "6",
        "streak": "53",
        "streams": "332,545",
        "youtubeID": "4Ez2wJnlwag"
    },
    {
        "ranking": "8",
        "title": "LA VILLA",
        "artist": null,
        "image": "https://lh3.googleusercontent.com/EvsdRJMaXWPTLCHVTw8aYQMlQJkJcE6pIT-jF9n5oxnBejfiWiFIErdyjfRqWdbnKfqYA6BA6-omwip5QQ=w180-h180-l90-rj",
        "prev": "7",
        "streak": "4",
        "streams": "332,072",
        "youtubeID": "EochZ-iyrqQ"
    },
    {
        "ranking": "9",
        "title": "Cuando No Era Cantante",
        "artist": null,
        "image": "https://lh3.googleusercontent.com/fiZPfKlY2eLZaF3Ev5rXWtUmRPKREVWhhxqYoeIvgH1HMY0tIDIElz1OYRfmO65PAkA33OKrQA8yjA1E=w180-h180-l90-rj",
        "prev": "8",
        "streak": "6",
        "streams": "320,374",
        "youtubeID": "AQJoTLhIUfQ"
    },
    {
        "ranking": "10",
        "title": "Frecuencia",
        "artist": null,
        "image": "https://lh3.googleusercontent.com/6yo7bduDl8ZkSpJqvHjR4-0pfTzwPyQFOAKBD9GojCZvQ090w2j_cYgeE_OXAdU5GeWLaV6C2kKaOCqs=w180-h180-l90-rj",
        "prev": "10",
        "streak": "31",
        "streams": "295,475",
        "youtubeID": "ebXEaHEYYng"
    },
    {
        "ranking": "11",
        "title": "Polos Opuestos",
        "artist": null,
        "image": "https://lh3.googleusercontent.com/8FkB4Xmkc7qgZjYNiObn-C-muo7CfpArMRPcFlwADOUrskDnHppPMcj6DgSTTnpsvAZbpw5HCfzvLjEH=w180-h180-l90-rj",
        "prev": "12",
        "streak": "7",
        "streams": "285,519",
        "youtubeID": "KZNFHwXzVXg"
    },
    {
        "ranking": "12",
        "title": "Ansiedad",
        "artist": null,
        "image": "https://lh3.googleusercontent.com/BG9_JhxsLEMcnR6tjVqCgg-QlhvAFSsAvVDs08Z-mnSgw_NrBDQL1qwvH9cmMxGQVb6ILGLcfWNLhdY=w180-h180-l90-rj",
        "prev": "11",
        "streak": "52",
        "streams": "277,620",
        "youtubeID": "Qm0q7YpYt-A"
    },
    {
        "ranking": "13",
        "title": "Marlboro Rojo",
        "artist": null,
        "image": "https://lh3.googleusercontent.com/wcctzBOL_SevQ9q9eq-J1V1fnQluovKWND7x5U3aYJLijtTeBXOIMICPrMnHQGL6FmOzasTAv6DsT79V=w180-h180-l90-rj",
        "prev": "9",
        "streak": "36",
        "streams": "269,882",
        "youtubeID": "ddkbVYutRXA"
    },
    {
        "ranking": "14",
        "title": "YOGURCITO REMIX (feat. ROA & Yan Block)",
        "artist": null,
        "image": "https://lh3.googleusercontent.com/UMM_UutDZpFdatYySdCu8a_vBYEteiChMHYmlP6QdEAKADK0XsChfGWFR0TzGsxGVbzUXGoqlGJuDSmrxg=w180-h180-l90-rj",
        "prev": "14",
        "streak": "22",
        "streams": "244,989",
        "youtubeID": "B7P8NMCAby8"
    },
    {
        "ranking": "15",
        "title": "COQUETA",
        "artist": null,
        "image": "https://lh3.googleusercontent.com/llYLq4jy6rSfhDDnEwL5rsxS80eBMvPzcZoryVzEQhbZCCOJMgcrkhtWiXTMLnASubnA0Ga99l6lVdUg=w180-h180-l90-rj",
        "prev": "15",
        "streak": "47",
        "streams": "219,443",
        "youtubeID": "nNUiVCKu_9Y"
    },
    {
        "ranking": "16",
        "title": "Uy Ay",
        "artist": null,
        "image": "https://lh3.googleusercontent.com/dV0V2gEwgpNH8j27iGuA3FmsybNyxlenCE9C9mNrJQEtJtzIGgXYR4pEEyV3ccKJT0okGBCfu_4fEBwL=w180-h180-l90-rj",
        "prev": "18",
        "streak": "15",
        "streams": "197,289",
        "youtubeID": "XmelMHaXZH4"
    },
    {
        "ranking": "17",
        "title": "Que Te Quieran Bonito",
        "artist": null,
        "image": "https://lh3.googleusercontent.com/9LArxydliRHVdB5dHtX4J-Iu6pD7T9DgXwZO9ThFuULrN2ARcjfZILv9y8_Bifo5Sgp4QeW8ac6QJYf0BQ=w180-h180-l90-rj",
        "prev": "16",
        "streak": "7",
        "streams": "196,721",
        "youtubeID": "qtlb5xu1XBw"
    },
    {
        "ranking": "18",
        "title": "ANSIEDAD",
        "artist": null,
        "image": "https://lh3.googleusercontent.com/wcctzBOL_SevQ9q9eq-J1V1fnQluovKWND7x5U3aYJLijtTeBXOIMICPrMnHQGL6FmOzasTAv6DsT79V=w180-h180-l90-rj",
        "prev": "13",
        "streak": "36",
        "streams": "195,655",
        "youtubeID": "UStUu4Ew3SU"
    },
    {
        "ranking": "19",
        "title": "POR SUS BESOS",
        "artist": null,
        "image": "https://lh3.googleusercontent.com/C7XPM3F-TnfHLgHhyqt7ZO0ftyWufIlCx0H5d465I-T7hAHRDy4uu2jsWhoQIJiih3FhmGADy9oSQWUh=w180-h180-l90-rj",
        "prev": "20",
        "streak": "27",
        "streams": "195,214",
        "youtubeID": "F1sLPnWV6Jk"
    },
    {
        "ranking": "20",
        "title": "quédate",
        "artist": null,
        "image": "https://lh3.googleusercontent.com/KPnrDQPK5rnyizSVXfxwHJWgnpIwn2jEp4_hJDay-EcgcW01vmnj8BxlgwuBgfXgS3I-5o0f1_KP2tc=w180-h180-l90-rj",
        "prev": "17",
        "streak": "35",
        "streams": "189,906",
        "youtubeID": "0ElD2qJ5ZoU"
    },
    {
        "ranking": "21",
        "title": "444 (Remix)",
        "artist": null,
        "image": "https://lh3.googleusercontent.com/OxIHPBfAIbfmu4r391qABKrmsWcu5RTeBqEEpNuD5fp__rDMW-AQ4Mb7o3SFCJB6wimrgS6kKcQCdUs8=w180-h180-l90-rj",
        "prev": "23",
        "streak": "29",
        "streams": "186,847",
        "youtubeID": "v6Ga63b2Q-E"
    },
    {
        "ranking": "22",
        "title": "TU SANCHO",
        "artist": null,
        "image": "https://i.ytimg.com/vi/a_H0K9W984E/default.jpg",
        "prev": "19",
        "streak": "34",
        "streams": "184,580",
        "youtubeID": "a_H0K9W984E"
    },
    {
        "ranking": "23",
        "title": "KERRIKO",
        "artist": null,
        "image": "https://lh3.googleusercontent.com/_YbwKfdFau4Z1FoGggRYshJZwDrNMlqhxTjRMTvqH1lnWN7zVIT1bCc2Ypro_HGbhCseR6lUL5rxBv2SyA=w180-h180-l90-rj",
        "prev": "22",
        "streak": "44",
        "streams": "175,752",
        "youtubeID": "FoBsqBmZiSk"
    },
    {
        "ranking": "24",
        "title": "Dices",
        "artist": null,
        "image": "https://lh3.googleusercontent.com/q6bMYrWyrG3vP0Q93WNA07NkAZ1KCpTtkNMRypGlO-rmvRneueY6mh0m-NBuy2fgwTxSAcjc32t8_BDh=w180-h180-l90-rj",
        "prev": "26",
        "streak": "15",
        "streams": "173,140",
        "youtubeID": "u5e8SfEOqpI"
    },
    {
        "ranking": "25",
        "title": "Pum Pum Shorts",
        "artist": null,
        "image": "https://lh3.googleusercontent.com/lKLMCPWVcSKGgrxLvhpiB_g6kahdsvd2-eVumLmW3CwmWd0a71AtVf55AydENqNiuQWKm1q3dRlcTGOgfA=w180-h180-l90-rj",
        "prev": "21",
        "streak": "16",
        "streams": "172,963",
        "youtubeID": "Zv42tc4Z9m8"
    },
    {
        "ranking": "26",
        "title": "Cositas Que Haciamos",
        "artist": null,
        "image": "https://lh3.googleusercontent.com/mr3Ngq8YRCCwBcB-7GcS9uQlrVLlSbgeP3p1d7WvBue7IjDPnw595iGOtj0-IT3IYh78v5kVkzTYSf6a=w180-h180-l90-rj",
        "prev": "31",
        "streak": "36",
        "streams": "161,363",
        "youtubeID": "VceA2FfMkFk"
    },
    {
        "ranking": "27",
        "title": "Actos De Un Tonto",
        "artist": null,
        "image": "https://lh3.googleusercontent.com/YR6eHBNGMDK-4mrCjqLdCrwfF8TW-0I3u76wEed7KhOS97WbK5hwdJOKKHu2JBloBPG0jtNEUJPMZK0=w180-h180-l90-rj",
        "prev": "30",
        "streak": "40",
        "streams": "158,763",
        "youtubeID": "wqupkfo4aO8"
    },
    {
        "ranking": "28",
        "title": "top diesel",
        "artist": null,
        "image": "https://lh3.googleusercontent.com/KPnrDQPK5rnyizSVXfxwHJWgnpIwn2jEp4_hJDay-EcgcW01vmnj8BxlgwuBgfXgS3I-5o0f1_KP2tc=w180-h180-l90-rj",
        "prev": "27",
        "streak": "34",
        "streams": "156,893",
        "youtubeID": "8H61_9M6IUs"
    },
    {
        "ranking": "29",
        "title": "Golden",
        "artist": null,
        "image": "https://lh3.googleusercontent.com/1U-1pXbvkpvGXGUIFs5m6RXz4Fmdvqo1zzQw8eY7b4G9iwpE6vaRclt8Ov5CS8ldROIQGu2InpGuSJSW=w180-h180-l90-rj",
        "prev": "24",
        "streak": "25",
        "streams": "152,122",
        "youtubeID": "yebNIHKAC4A"
    },
    {
        "ranking": "30",
        "title": "dopamina",
        "artist": null,
        "image": "https://lh3.googleusercontent.com/i3Udyi0Ev7iwmB6MbEkx3LMFv1TgigJ1CL7c-25roEMWUJUZm8FkCTIMj7RiMdg8ZNqISRDmCFHZsjQ=w180-h180-l90-rj",
        "prev": "39",
        "streak": "3",
        "streams": "150,656",
        "youtubeID": "guFFBwipASU"
    },
    {
        "ranking": "31",
        "title": "La Plena (W Sound 05)",
        "artist": null,
        "image": "https://lh3.googleusercontent.com/58MvPSGUVFo_Wn_3hbVI4QhTD_v-peEC4jFFrFzor1OHN8F79tRLRaCBRcBVz7cKWO2sYhvWp-lweeRBzA=w180-h180-l90-rj",
        "prev": "28",
        "streak": "44",
        "streams": "147,527",
        "youtubeID": "F1_aOX0acbY"
    },
    {
        "ranking": "32",
        "title": "Necio (feat. Santana)",
        "artist": null,
        "image": "https://lh3.googleusercontent.com/k6CjUshafSvhyNfNJn-jQxUAYJU261qFDLqI4rFN_deD7fyA6ehvU3H7ZYL2xz8WfMXi0_WTKMHIuUZMAA=w180-h180-l90-rj",
        "prev": "40",
        "streak": "39",
        "streams": "143,723",
        "youtubeID": "DXiXPhvYuNU"
    },
    {
        "ranking": "33",
        "title": "Zoo",
        "artist": null,
        "image": "https://lh3.googleusercontent.com/rGuCC6uOZuWpa_zvCU2hAmKAr0Pzs0cMAJ702w4zi1Og1QyxJLagnxC8VXAsW_LGkyrFZZ5ZuGylbbnvMg=w180-h180-l90-rj",
        "prev": "35",
        "streak": "6",
        "streams": "139,514",
        "youtubeID": "Kw3935PH01E"
    },
    {
        "ranking": "34",
        "title": "Martes de Galería (feat. De La Ghetto)",
        "artist": null,
        "image": "https://lh3.googleusercontent.com/OigXfEfs-ds51hx7ruYBSt-fm_B7LvAPhewG_Lk7BXwv_jzPBNE9CMRAG9i-kWYUtFW2JArOxTuY4jXu=w180-h180-s-l90-rj",
        "prev": "50",
        "streak": "22",
        "streams": "138,779",
        "youtubeID": "yw1BI7OtN_U"
    },
    {
        "ranking": "35",
        "title": "TATTOO",
        "artist": null,
        "image": "https://lh3.googleusercontent.com/3X1-elZWcokldoHCSvFL3lpdWLpJT_LThRnikRM-uiOu-_H64H9hHtLeQp6ByFyHd9Z1aMDrlO370Uio_g=w180-h180-l90-rj",
        "prev": "38",
        "streak": "41",
        "streams": "138,434",
        "youtubeID": "1yZFLRJ4F0Q"
    },
    {
        "ranking": "36",
        "title": "DtMF",
        "artist": null,
        "image": "https://lh3.googleusercontent.com/yBcpSTWxVqyJr7enMy7HFv14Yb8p1jI5AS5o49Cvbeyc6zjvCvdLn_0_iAxz50MqxLx6hQDngWBeaC26=w180-h180-l90-rj",
        "prev": "33",
        "streak": "29",
        "streams": "134,395",
        "youtubeID": "v9T_MGfzq7I"
    },
    {
        "ranking": "37",
        "title": "El Mejor (Remix)",
        "artist": null,
        "image": "https://lh3.googleusercontent.com/bUS2EpDW1p6g53vHU1NILq_V6Xe5E4k78m_JdbKSht2L7GHk5JQYQx65PfVzPfUfWMKQXroDFQyf-_5aHQ=w180-h180-l90-rj",
        "prev": "-",
        "streak": "1",
        "streams": "132,045",
        "youtubeID": "aPQN_xOCfvg"
    },
    {
        "ranking": "38",
        "title": "Te Quiero Igual Que Ayer",
        "artist": null,
        "image": "https://lh3.googleusercontent.com/VuxqQ4vRayT8h5oKvEt-jORo7TlRdfIvykfVNCZXY2fX0wSWITb12QDi36IfMCePqReF9f95JVOczZeR=w180-h180-l90-rj",
        "prev": "36",
        "streak": "26",
        "streams": "131,845",
        "youtubeID": "8sCWmb8f-BY"
    },
    {
        "ranking": "39",
        "title": "EL PIZON",
        "artist": null,
        "image": "https://lh3.googleusercontent.com/ZHkIDP-Aaic5qFEzxaraWYJoUdNU1kqWXV_qti1O5JinOy9JvZx4cZP40B4BfzYPc45TD7J7RWI6lSIz-Q=w180-h180-l90-rj",
        "prev": "41",
        "streak": "23",
        "streams": "129,595",
        "youtubeID": "SQrQTB4S4jU"
    },
    {
        "ranking": "40",
        "title": "Siempre Me Llama (Remix) (feat. YAVIAH)",
        "artist": null,
        "image": "https://lh3.googleusercontent.com/d6fn4HU8MToHjM6QURzjwH8mA235iZMZ7YgSkDRUIz-1py_sWsMmV6CyA-3E5l1RX1Z_U78rYlO3V6A=w180-h180-l90-rj",
        "prev": "59",
        "streak": "3",
        "streams": "129,534",
        "youtubeID": "KJaxU5rDqxY"
    },
    {
        "ranking": "41",
        "title": "MARIA SALOME",
        "artist": null,
        "image": "https://lh3.googleusercontent.com/ckB6BK_nlQPa0lmCWcUA1BCqkJJfrC_5erqu6ZjWpdfkjfqVRTWQHtxYNMl-Cj6beyy8BuuDJ4JrNnA=w180-h180-l90-rj",
        "prev": "44",
        "streak": "17",
        "streams": "128,690",
        "youtubeID": "pDfVd9LIHgg"
    },
    {
        "ranking": "42",
        "title": "Dardos",
        "artist": null,
        "image": "https://lh3.googleusercontent.com/Ojrlr9fjHRwlbR6iz2oeVsUmtzG7FswNrH-cnQCbnUe9SiRApumcqzVwNNM5wFUiLxaZKGeT3clUKVBtyg=w180-h180-l90-rj",
        "prev": "29",
        "streak": "3",
        "streams": "126,630",
        "youtubeID": "D6XR9GfBfwY"
    },
    {
        "ranking": "43",
        "title": "Ba Ba Bad Remix",
        "artist": null,
        "image": "https://lh3.googleusercontent.com/NwjDsRFpuYo2YZqVwxscKafK1Sts-xig8KAqHSK9vM7t0ics5SzL8g331OQ4kVhnAt4oPka8Gcb1debwlw=w180-h180-l90-rj",
        "prev": "42",
        "streak": "25",
        "streams": "121,492",
        "youtubeID": "dn3d8awSA0c"
    },
    {
        "ranking": "44",
        "title": "Y Qué Me Importa",
        "artist": null,
        "image": "https://i.ytimg.com/vi/tcNTF1Sywo4/default.jpg",
        "prev": "43",
        "streak": "31",
        "streams": "121,281",
        "youtubeID": "tcNTF1Sywo4"
    },
    {
        "ranking": "45",
        "title": "Adicto",
        "artist": null,
        "image": "https://lh3.googleusercontent.com/hWUNXLhYIQAB9N1wv1SCDjWROgHhZjfgGGcLPBMXyMxypWvPLK3nViUYt7hZP2e2JZA_t1FUYkmEMFI=w180-h180-l90-rj",
        "prev": "53",
        "streak": "58",
        "streams": "119,456",
        "youtubeID": "58u-zkDLNPg"
    },
    {
        "ranking": "46",
        "title": "El Party Está Full",
        "artist": null,
        "image": "https://lh3.googleusercontent.com/ZoQHdHu9_tX4MTQNSGbHaZF427P6CEhsIJNeu_Gnxr5DLS_14kPuUFmf-GkEf6nI6njEsTDoU7n2QPnc=w180-h180-l90-rj",
        "prev": "46",
        "streak": "22",
        "streams": "115,578",
        "youtubeID": "WPsh1NOuA0E"
    },
    {
        "ranking": "47",
        "title": "NO ME QUIERO CASAR",
        "artist": null,
        "image": "https://lh3.googleusercontent.com/wLNbSrba-Qu4IFD4zLkjmxn2IqtDN1tQEWSh_QgrlBTy1GhDLai3JGjEmQ9K-6sWttkzQFBrmO2Mj4_1iw=w180-h180-l90-rj",
        "prev": "37",
        "streak": "21",
        "streams": "115,216",
        "youtubeID": "c5wXFxiLabI"
    },
    {
        "ranking": "48",
        "title": "Montagem Miau",
        "artist": null,
        "image": "https://i.ytimg.com/vi/JJjEl_EVsLA/default.jpg",
        "prev": "45",
        "streak": "9",
        "streams": "113,772",
        "youtubeID": "JJjEl_EVsLA"
    },
    {
        "ranking": "49",
        "title": "Vuelve Mami",
        "artist": null,
        "image": "https://lh3.googleusercontent.com/PebX2TjNow1Zg8l65-InNGRxikYznX2yoMy0tMlHmWFemVVW8ReixD-PFF1mh5GTEZyM-k1VPG__-a4=w180-h180-l90-rj",
        "prev": "48",
        "streak": "25",
        "streams": "113,513",
        "youtubeID": "SRDkwORUPak"
    },
    {
        "ranking": "50",
        "title": "Tu Peor Error",
        "artist": null,
        "image": "https://lh3.googleusercontent.com/9rNAV-kprrTrWhGhIKGy9fkhCLuU4lpjyM7zcv-kEZEM6NINiBJ7plwgy0Hpc0_6v9kCUIBV7P8GQBwiOA=w180-h180-l90-rj",
        "prev": "-",
        "streak": "25",
        "streams": "112,366",
        "youtubeID": "kM5YgQBD3rE"
    },
    {
        "ranking": "51",
        "title": "18 Libras",
        "artist": null,
        "image": "https://lh3.googleusercontent.com/mAC2k7jNMhMzeZYEU815XgNkcFrdjDK8aaqjYFWQ15k4MwdVeh5uJJz0JgSYRSMLwbcBbgOifTb7jRo=w180-h180-l90-rj",
        "prev": "68",
        "streak": "16",
        "streams": "109,073",
        "youtubeID": "2cPtcFYpx_k"
    },
    {
        "ranking": "52",
        "title": "En El Muelle de San Blas",
        "artist": null,
        "image": "https://lh3.googleusercontent.com/TMQyIrxGpe27eB3v5hoMhJ1z2nuYBdJR3w2lrsWPB_dvOYW2bhR6OzoZBP9hvKKJTMA_5sEfQIZ-8uc=w180-h180-l90-rj",
        "prev": "62",
        "streak": "31",
        "streams": "108,703",
        "youtubeID": "teprNzF6J1I"
    },
    {
        "ranking": "53",
        "title": "GOZALO",
        "artist": null,
        "image": "https://i.ytimg.com/vi/_LtAZDujqIw/default.jpg",
        "prev": "74",
        "streak": "2",
        "streams": "107,759",
        "youtubeID": "_LtAZDujqIw"
    },
    {
        "ranking": "54",
        "title": "Si Tu Presencia Conmigo No Va (En Vivo) (feat. Marcos Yaroide)",
        "artist": null,
        "image": "https://lh3.googleusercontent.com/h6IgiIoh5yMKbGcv5cdZ6bWnr1CCrhKrkn0oxOlk--r02zpEXoTxSi7r7moOm4uQhrJ8AaP70AmVmHM=w180-h180-l90-rj",
        "prev": "55",
        "streak": "56",
        "streams": "107,137",
        "youtubeID": "j2jA71Vorjk"
    },
    {
        "ranking": "55",
        "title": "El Que Te Amó",
        "artist": null,
        "image": "https://lh3.googleusercontent.com/FHbrcUSV79z4MLHcz5Tf07ajh2e7y7Kf779PslJkirTF3pxPdSLkRFbsa8ccKpwU26_BUYFhIsscmm4=w180-h180-l90-rj",
        "prev": "60",
        "streak": "15",
        "streams": "106,805",
        "youtubeID": "K2_iTMvLylc"
    },
    {
        "ranking": "56",
        "title": "Hace Mucho Tiempo",
        "artist": null,
        "image": "https://lh3.googleusercontent.com/ZLFzYZKsuBq8_Y13uWA4709NDCGnuFMyTDDb8JspXUkICuN48wZoiR3FJ0f-3Dg30rTLrEVFsS_50xJF=w180-h180-l90-rj",
        "prev": "58",
        "streak": "28",
        "streams": "104,268",
        "youtubeID": "TImHWyOyok0"
    },
    {
        "ranking": "57",
        "title": "daño",
        "artist": null,
        "image": "https://lh3.googleusercontent.com/i3Udyi0Ev7iwmB6MbEkx3LMFv1TgigJ1CL7c-25roEMWUJUZm8FkCTIMj7RiMdg8ZNqISRDmCFHZsjQ=w180-h180-l90-rj",
        "prev": "52",
        "streak": "3",
        "streams": "102,369",
        "youtubeID": "5dsi4mTwzYs"
    },
    {
        "ranking": "58",
        "title": "Santo por siempre (En vivo)",
        "artist": null,
        "image": "https://lh3.googleusercontent.com/F8n9JY66JAw-6vkAqDUPOTcL8EUcsf6VG23m-G_D5MrqmEV2tNEpMu8d06twtc4V3F97SlJU5zuuMZXB=w180-h180-l90-rj",
        "prev": "-",
        "streak": "22",
        "streams": "101,912",
        "youtubeID": "1CxEg0H6Q-4"
    },
    {
        "ranking": "59",
        "title": "NO CRY",
        "artist": null,
        "image": "https://lh3.googleusercontent.com/M6jEB1HHMHwOM5K18iz0ptqqh7DkwD-t4vYV7OUqgJuh6hDkUG6m5iWdyPUvzlBx4HIvf7tcT56r_RwAkQ=w180-h180-l90-rj",
        "prev": "56",
        "streak": "4",
        "streams": "101,855",
        "youtubeID": "rcW-QwI7nAc"
    },
    {
        "ranking": "60",
        "title": "Sola (Remix) (feat. Daddy Yankee, Wisin, Farruko & Zion & Lennox)",
        "artist": null,
        "image": "https://lh3.googleusercontent.com/dutAMV94rcplywzhf9h_mMQyWuj03_f6bGb1P4cyH8cnTx_cA8_KJ7mwQYKxUg-fEMFLhFj2siOcyaY=w180-h180-s-l90-rj",
        "prev": "-",
        "streak": "45",
        "streams": "101,139",
        "youtubeID": "06Cwz1oUFV4"
    },
    {
        "ranking": "61",
        "title": "Que Sensación (Remix)",
        "artist": null,
        "image": "https://lh3.googleusercontent.com/Ii-bdI_EnAHvWg-sETRcDJy4p_PVquaetSicfEN-OHpsL2WpfbDwAJtDUUfIETCw-j9g88Zkf5d_bXbn=w180-h180-l90-rj",
        "prev": "54",
        "streak": "10",
        "streams": "98,802",
        "youtubeID": "z7Y1scppIV0"
    },
    {
        "ranking": "62",
        "title": "7-3",
        "artist": null,
        "image": "https://lh3.googleusercontent.com/i3Udyi0Ev7iwmB6MbEkx3LMFv1TgigJ1CL7c-25roEMWUJUZm8FkCTIMj7RiMdg8ZNqISRDmCFHZsjQ=w180-h180-l90-rj",
        "prev": "-",
        "streak": "1",
        "streams": "97,337",
        "youtubeID": "7rH1JlCz2hg"
    },
    {
        "ranking": "63",
        "title": "El Papel Cambio",
        "artist": null,
        "image": "https://www.youtube.com/s/charts/images/top_songs.png",
        "prev": "64",
        "streak": "41",
        "streams": "97,222",
        "youtubeID": null
    },
    {
        "ranking": "64",
        "title": "CHAVALITAS",
        "artist": null,
        "image": "https://lh3.googleusercontent.com/wcctzBOL_SevQ9q9eq-J1V1fnQluovKWND7x5U3aYJLijtTeBXOIMICPrMnHQGL6FmOzasTAv6DsT79V=w180-h180-l90-rj",
        "prev": "51",
        "streak": "8",
        "streams": "96,928",
        "youtubeID": "1lulHw7LKl4"
    },
    {
        "ranking": "65",
        "title": "ENTRE GOLPES Y BESOS",
        "artist": null,
        "image": "https://lh3.googleusercontent.com/12VTZ1b3hdifP6q2SFOQsIzOtQrMUSiaLoJ8DS53ZFbMcrIy0U9N4fclL5DsP31z27tKT8OH_PdmVguO=w180-h180-l90-rj",
        "prev": "72",
        "streak": "20",
        "streams": "96,690",
        "youtubeID": "rW4RYGiICBU"
    },
    {
        "ranking": "66",
        "title": "Mi Último Deseo",
        "artist": null,
        "image": "https://lh3.googleusercontent.com/oQ5jgVEhq0DPXQOs2ktf6QpR7AVhb1boIBeHT9z_nPFzj8l1D1TXwzH5Pyr48kgqwwpaS1XOjuD4UJiY=w180-h180-l90-rj",
        "prev": "-",
        "streak": "27",
        "streams": "95,765",
        "youtubeID": "cVlAmP-KDT4"
    },
    {
        "ranking": "67",
        "title": "Prometiste Volver",
        "artist": null,
        "image": "https://lh3.googleusercontent.com/xdJB2Y8ThzCH1wIf0yXKLf_S6uEZjH7QfvZ3cNcFdM7m5-QqhGAcXZy8h3afD2vEg3BDZhB-emxtui8sMA=w180-h180-l90-rj",
        "prev": "78",
        "streak": "15",
        "streams": "93,912",
        "youtubeID": "JPwxYDhyjbY"
    },
    {
        "ranking": "68",
        "title": "Pasta",
        "artist": null,
        "image": "https://lh3.googleusercontent.com/XZXn_e5lXhwXSxWrg8rbW2oOXH3FSX9H5DS4Plopg1_F-rL3f4xCy2BJ6b4CNnNOVVYryM1QJm5_7izQWA=w180-h180-l90-rj",
        "prev": "61",
        "streak": "20",
        "streams": "93,746",
        "youtubeID": "iHNscGNVbFY"
    },
    {
        "ranking": "69",
        "title": "ACAPULCO TROPICAL",
        "artist": null,
        "image": "https://lh3.googleusercontent.com/9hjU0R3P4yOag8JJlBDrqhGr57V13esD-51A5YrExYv1ZC4H9lAwNImIYHJCluN69052iEKjxYjmMOMKiQ=w180-h180-l90-rj",
        "prev": "76",
        "streak": "4",
        "streams": "93,068",
        "youtubeID": "kNzCqBA9Bho"
    },
    {
        "ranking": "70",
        "title": "No Se De Ella \"My Space\"",
        "artist": null,
        "image": "https://lh3.googleusercontent.com/_CYs54S18P3trTbIUyZ_RhLVDgHlCYa2c0NQ5S98pjYzWFJpnt2XuHtQbJ6_2a2OHwwILaItUJB_RJUAGg=w180-h180-s-l90-rj",
        "prev": "77",
        "streak": "3",
        "streams": "92,538",
        "youtubeID": "W_iXH1w8-5Q"
    },
    {
        "ranking": "71",
        "title": "EL LECHERO",
        "artist": null,
        "image": "https://lh3.googleusercontent.com/a9zENn_akKjzFbcLDDRNQIk1fcVKso76segcj-SWWkdnfYVmTfKMCmn-Lq182J3JTFH-_a_v7NN_0u4=w180-h180-l90-rj",
        "prev": "86",
        "streak": "9",
        "streams": "91,826",
        "youtubeID": "l2tcxeqDbDg"
    },
    {
        "ranking": "72",
        "title": "Mi Entorno",
        "artist": null,
        "image": "https://lh3.googleusercontent.com/q2PViuwwI4gvWDq4lLKFkZdQoqFn6nXM-gLYc4AiCH26qupb0h3ug_mwayYpzIono-5yP4G5HmvwORkf=w180-h180-l90-rj",
        "prev": "63",
        "streak": "3",
        "streams": "91,514",
        "youtubeID": "OAu5vQ0S-Yo"
    },
    {
        "ranking": "73",
        "title": "Alégale Al Umpire",
        "artist": null,
        "image": "https://lh3.googleusercontent.com/xsvyR1L56MJMXHZ_OnGy3yI00pu-wG3awGICBhoyceSbSF-BwioUds6qpQXW_pHKSrE96Kyq-Jfys2A=w180-h180-l90-rj",
        "prev": "81",
        "streak": "15",
        "streams": "89,678",
        "youtubeID": "G321HYlJTM4"
    },
    {
        "ranking": "74",
        "title": "Salgo Pa' la Calle (feat. Randy  )",
        "artist": null,
        "image": "https://i.ytimg.com/vi/aXdfSK3seLM/default.jpg",
        "prev": "65",
        "streak": "10",
        "streams": "89,506",
        "youtubeID": "aXdfSK3seLM"
    },
    {
        "ranking": "75",
        "title": "Alguien Te Va a Hacer Llorar",
        "artist": null,
        "image": "https://i.ytimg.com/vi/a000MohPsFA/default.jpg",
        "prev": "75",
        "streak": "19",
        "streams": "89,477",
        "youtubeID": "a000MohPsFA"
    },
    {
        "ranking": "76",
        "title": "No Me Dejan Verla (En Vivo)",
        "artist": null,
        "image": "https://lh3.googleusercontent.com/PiXiWAjmg4U_dBshO9Ivw_bdNYgXaVdCe4iRyQ88uvjIzr8eb3fTE4MMbno4NspqKnw7EUcdGw2s1Z8=w180-h180-l90-rj",
        "prev": "80",
        "streak": "17",
        "streams": "89,328",
        "youtubeID": "GTSeVSfOmZg"
    },
    {
        "ranking": "77",
        "title": "Te Metiste en Mi Piel (Recopilación)",
        "artist": null,
        "image": "https://i.ytimg.com/vi/wTrcts0cgno/default.jpg",
        "prev": "70",
        "streak": "4",
        "streams": "88,524",
        "youtubeID": "wTrcts0cgno"
    },
    {
        "ranking": "78",
        "title": "Mojada",
        "artist": null,
        "image": "https://lh3.googleusercontent.com/Urw14AyU995KoP1xTf8bqsUk2TlfL9zdAJwzM33vcLo9BG1PGz1IFFvnlCobBrvk6ZSgU8-u5aG1lR23=w180-h180-l90-rj",
        "prev": "85",
        "streak": "12",
        "streams": "88,461",
        "youtubeID": "q94Q1z_Ruds"
    },
    {
        "ranking": "79",
        "title": "Se Fue La Pantera (feat. Banda La Indicada)",
        "artist": null,
        "image": "https://lh3.googleusercontent.com/IxieOANCCi9Y_GTq3NIkIqHbfxmrdHg1k2RclitFS7hONkPZAJ_Fem6SmPyYgX0s_D4HadkC3hQGuGM=w180-h180-l90-rj",
        "prev": "92",
        "streak": "4",
        "streams": "87,794",
        "youtubeID": "Oc8tXfQJFaE"
    },
    {
        "ranking": "80",
        "title": "Muévelo",
        "artist": null,
        "image": "https://lh3.googleusercontent.com/ZY-T6RNMwjNJ-uqkACc0Qx3c3va5tpzZTjMg5gZlRbkcFyRmg9p8BWVnAxI5o55mHNnzmkkpNtH-uCXgvA=w180-h180-l90-rj",
        "prev": "57",
        "streak": "2",
        "streams": "87,322",
        "youtubeID": "m3Fy2OrSDiQ"
    },
    {
        "ranking": "81",
        "title": "El Teléfono",
        "artist": null,
        "image": "https://lh3.googleusercontent.com/RVcF23w_FFqs_XYa6LLS9UdMMvnQgvGw6PHaI4vlsrV0Hj-J4tYiMQI-uacrvm_BzjsUJhVMkBmuMWzKsg=w180-h180-l90-rj",
        "prev": "73",
        "streak": "11",
        "streams": "86,305",
        "youtubeID": "c4RQzcPxTpw"
    },
    {
        "ranking": "82",
        "title": "El Taxi (feat. Pitbull & Sensato)",
        "artist": null,
        "image": "https://lh3.googleusercontent.com/Kmxick-AfTR7iHOby0d1clWWl2xdZYeWJ5u8k4ZVyocufPvP1zzSnTf1UnXmF4U2fkUVnu2hGch2Hy8=w180-h180-l90-rj",
        "prev": "71",
        "streak": "18",
        "streams": "85,589",
        "youtubeID": "qRp3-D3SMwI"
    },
    {
        "ranking": "83",
        "title": "Fuera Del Planeta (Remix)",
        "artist": null,
        "image": "https://lh3.googleusercontent.com/_c3gDj8ZblCtn-xwlUziK1fVpAF8dV-0r_Y3hDY9WfRdjv-JJziepVQlWMyT7wUAHi1ugncSJOi83bi1=w180-h180-l90-rj",
        "prev": "94",
        "streak": "4",
        "streams": "84,949",
        "youtubeID": "HAc3f0BUfo0"
    },
    {
        "ranking": "84",
        "title": "Wuirra Pi$Ona (Remix) (feat. MASCA)",
        "artist": null,
        "image": "https://lh3.googleusercontent.com/qeZOIkAbPURufAPUQnDIPaW0OOXkBflvZ6dqSQYtT9L_DCbFH6TsWB9QArZM8JxM0A7lvWawbkJmSVh7=w180-h180-l90-rj",
        "prev": "67",
        "streak": "6",
        "streams": "84,287",
        "youtubeID": "q8XV5L5UGxU"
    },
    {
        "ranking": "85",
        "title": "DÓNDE",
        "artist": null,
        "image": "https://lh3.googleusercontent.com/M6jEB1HHMHwOM5K18iz0ptqqh7DkwD-t4vYV7OUqgJuh6hDkUG6m5iWdyPUvzlBx4HIvf7tcT56r_RwAkQ=w180-h180-l90-rj",
        "prev": "84",
        "streak": "15",
        "streams": "83,262",
        "youtubeID": "15kHmaNg0Q0"
    },
    {
        "ranking": "86",
        "title": "FANTASÍA",
        "artist": null,
        "image": "https://lh3.googleusercontent.com/iftmn4bwrHCjj7r32wuRRUZLEfbhm4yNBca92wldj9ykzZ5v65apqq8Qcnku2-H_uqulwcxTgkcwt4uk=w180-h180-l90-rj",
        "prev": "89",
        "streak": "5",
        "streams": "83,253",
        "youtubeID": "feFKZjh8Xlo"
    },
    {
        "ranking": "87",
        "title": "El Próximo Viernes",
        "artist": null,
        "image": "https://lh3.googleusercontent.com/g0Q5Etf_2swx9_1u0YZZHmnEVMW-2R6AKPZ7d_F93vm4B-S9M6X4xUmVQE2saT-FhlIz-I93xx3rS4QR=w180-h180-l90-rj",
        "prev": "79",
        "streak": "9",
        "streams": "82,840",
        "youtubeID": "79xXIGiltEo"
    },
    {
        "ranking": "88",
        "title": "Rayando el Sol",
        "artist": null,
        "image": "https://lh3.googleusercontent.com/wmdgXJygvXS9i60TIUvIU9vA-8VHx2Gx3thScz3H26j35r8DMrLc4bi9-GNAokk7TWr82CbpouZaKBTc=w180-h180-l90-rj",
        "prev": "82",
        "streak": "12",
        "streams": "82,119",
        "youtubeID": "FnxWAhvhSEw"
    },
    {
        "ranking": "89",
        "title": "Cedí",
        "artist": null,
        "image": "https://lh3.googleusercontent.com/fqWIDjVdcbRI2D4gRbdkfcUUbRmoANOpQ6SsPvXiEOB9i1H-9NmwatPQPdk5LAuq2E4QIQTMKV1qjS1p=w180-h180-l90-rj",
        "prev": "97",
        "streak": "5",
        "streams": "81,953",
        "youtubeID": "DFmPyWTKAFc"
    },
    {
        "ranking": "90",
        "title": "Perdido",
        "artist": null,
        "image": "https://lh3.googleusercontent.com/8z615697TJH9uiiHeT31a3GUmtWz5oEECO-4RJoqsee6184S_HkkcKib_OFE_w_LMcxXhF0MO_RmSCadgQ=w180-h180-l90-rj",
        "prev": "100",
        "streak": "4",
        "streams": "81,065",
        "youtubeID": "FohoNEGLfQQ"
    },
    {
        "ranking": "91",
        "title": "Llamada De Mi Ex",
        "artist": null,
        "image": "https://lh3.googleusercontent.com/jxn0p24szRmOD98ibl8xqQiG2ANTEQ0IoXWZSg7im3rWoL_b2-YUwOBvda_NMutN8ppZyhUNHhZQ_YDI=w180-h180-l90-rj",
        "prev": "99",
        "streak": "19",
        "streams": "80,837",
        "youtubeID": "Yx8m91tgjpw"
    },
    {
        "ranking": "92",
        "title": "Welcome To My Crib",
        "artist": null,
        "image": "https://lh3.googleusercontent.com/DFBpnnG6Znu3EPUXyB-73IGXvjNP6dbHBrFtebLbCQnoGoM-N2ayFMUyokiA1pba2n3RHFn-jjJjxhEfMQ=w180-h180-l90-rj",
        "prev": "95",
        "streak": "3",
        "streams": "80,756",
        "youtubeID": "RXE8McRo6Ms"
    },
    {
        "ranking": "93",
        "title": "EL MUÑECO (feat. Sangre Cardona)",
        "artist": null,
        "image": "https://lh3.googleusercontent.com/3fmMQuXM7fn09-tTnZP88ix-jIZll71XUEZrI_UaeicRZbIHLjK5_sHPkzXAG6y9_9I4N-Qku_NmDwQ=w180-h180-l90-rj",
        "prev": "-",
        "streak": "1",
        "streams": "79,676",
        "youtubeID": "Jy3r71j3pAk"
    },
    {
        "ranking": "94",
        "title": "NO BATIDÃO (SLOWED)",
        "artist": null,
        "image": "https://lh3.googleusercontent.com/eEXqI0KeotuaiRx4PjiopjPnlTBj9aiSXbY1NmzielYry7Mvs-WRANaJiivV62Zl6ufFtOwDMUtRmKVf=w180-h180-l90-rj",
        "prev": "-",
        "streak": "1",
        "streams": "79,222",
        "youtubeID": "MeOoJOt1P0Y"
    },
    {
        "ranking": "95",
        "title": "Mi Reina",
        "artist": null,
        "image": "https://lh3.googleusercontent.com/o2vaYX-_ptBIN6i99WZQ_0yZnbuaV8nKJhPH8M4HG3cPQxm7kGfS5492aVitTIvIDeuaoOy_2r7X2oO4=w180-h180-l90-rj",
        "prev": "-",
        "streak": "17",
        "streams": "79,066",
        "youtubeID": "dlM8hxCvOTc"
    },
    {
        "ranking": "96",
        "title": "Aunque Ahora Estés Con Él",
        "artist": null,
        "image": "https://lh3.googleusercontent.com/vAL7zUSByS4bE0B6FRq5gNvzWac6fSEMZVaaQrXSMX8E0i-zRLVVKw5vPMDXnpFGZL7xByM29aYXQLjB=w180-h180-l90-rj",
        "prev": "-",
        "streak": "6",
        "streams": "78,825",
        "youtubeID": "xpCWsiOukFw"
    },
    {
        "ranking": "97",
        "title": "Sin tu Amor (feat. Alexpro)",
        "artist": null,
        "image": "https://i.ytimg.com/vi/3Bo22-gtIoc/default.jpg",
        "prev": "-",
        "streak": "8",
        "streams": "78,742",
        "youtubeID": "3Bo22-gtIoc"
    },
    {
        "ranking": "98",
        "title": "Solos (feat. Plan B)",
        "artist": null,
        "image": "https://lh3.googleusercontent.com/Rwv1sAEqBFuKnIND9QBvfgq-CzBqhvOqxC5LbFEMMDnmCVR-wWXSGNF4Tlw8k-16a5IetCo6JOLHs0A=w180-h180-l90-rj",
        "prev": "98",
        "streak": "6",
        "streams": "78,506",
        "youtubeID": "BjdEyBF6V0U"
    },
    {
        "ranking": "99",
        "title": "Soy Una Gargola",
        "artist": null,
        "image": "https://i.ytimg.com/vi/GQp0bxDCojA/default.jpg",
        "prev": "-",
        "streak": "10",
        "streams": "78,342",
        "youtubeID": "GQp0bxDCojA"
    },
    {
        "ranking": "100",
        "title": "Piensas en Mí",
        "artist": null,
        "image": "https://lh3.googleusercontent.com/AXe7VPwUlo6_1-lrlvTvwUoAO0bFChL_rP8u4ch951FZ35qgRXRTLAbYBBzNUrgqXY6GcMUKmhCGus8=w180-h180-l90-rj",
        "prev": "-",
        "streak": "3",
        "streams": "78,128",
        "youtubeID": "pnEHsUWFuNM"
    }
]