[
    {
        "ranking": "1",
        "title": "Eller Üzer",
        "artist": null,
        "image": "https://yt3.googleusercontent.com/QDf6UeLd2LDHkhQyOCVh4t1Siqm0Cw9XGcenmtIG5ASuAzQXX16NiCy95z47_lQP_BW5AQiLd9zlJRah=w180-h180-l90-rj",
        "prev": "1",
        "streak": "12",
        "streams": "10,419,768",
        "youtubeID": "XScahAwKYHU"
    },
    {
        "ranking": "2",
        "title": "Hileli",
        "artist": null,
        "image": "https://yt3.googleusercontent.com/HVn6uh6o4jcmXw3jUEjmD2nTTjVBd200AnixeuL1j_1hkOz-mv3hrcHD4nxz-uABrNi7kGWSOl6P-FY=w180-h180-l90-rj",
        "prev": "2",
        "streak": "2",
        "streams": "8,538,316",
        "youtubeID": "kXKhNI4DLHM"
    },
    {
        "ranking": "3",
        "title": "Değilim",
        "artist": null,
        "image": "https://i.ytimg.com/vi/X9uWzkCC8DU/default.jpg",
        "prev": "23",
        "streak": "2",
        "streams": "4,926,312",
        "youtubeID": "X9uWzkCC8DU"
    },
    {
        "ranking": "4",
        "title": "ihtiyacım Var (Live)",
        "artist": null,
        "image": "https://yt3.googleusercontent.com/lby3wZTxoZea9zbm5DgMjcDirePzRGx6P-dpRz_g1mHsDhGJTT2fco0RHQS2-zMA3wbKvCNVt1r01mSb=w180-h180-l90-rj",
        "prev": "4",
        "streak": "4",
        "streams": "4,851,242",
        "youtubeID": "RVGyLcbyhOU"
    },
    {
        "ranking": "5",
        "title": "Daha İyi",
        "artist": null,
        "image": "https://yt3.googleusercontent.com/xvm6wZ_I903U5ASqGIXXevZ77g-b16SF3RwpwwWF78Oe5avTZXFHxFdJacY_-XpA4Y6n2RdCPetr-R0SIQ=w180-h180-l90-rj",
        "prev": "3",
        "streak": "7",
        "streams": "4,432,251",
        "youtubeID": "vso1LpaQRbo"
    },
    {
        "ranking": "6",
        "title": "Vursunlar (Roman Version)",
        "artist": null,
        "image": "https://yt3.googleusercontent.com/QhMOAC_ciO30HCjvQZnsOCViKf88cMgQnNKr3bVhMWAWBnG5uZa-epz5qiHsBfgayAQp_1wYROw2TOl7=w180-h180-l90-rj",
        "prev": "7",
        "streak": "57",
        "streams": "4,257,892",
        "youtubeID": "Rnsj-Yi9VOo"
    },
    {
        "ranking": "7",
        "title": "Çıkmaz Bir Sokakta",
        "artist": null,
        "image": "https://yt3.googleusercontent.com/igEV1AcOQsP52ha229mibIh5T7UtfuKbZZ7zGqWjteqyWcW4LXdJruof2L63I2kUfk2tTHgdTtCJKfSE=w180-h180-l90-rj",
        "prev": "6",
        "streak": "30",
        "streams": "3,959,241",
        "youtubeID": "cLygvXtuklI"
    },
    {
        "ranking": "8",
        "title": "Bir Daha Sevmek Yok",
        "artist": null,
        "image": "https://yt3.googleusercontent.com/LCOEIPNhg5Ene-wEPiuOPKygkASF-3M2mgDoFTCVd16o7WQiLxzfFiqLtX6pFiH5SU3dc4LRY28ix3M=w180-h180-l90-rj",
        "prev": "5",
        "streak": "5",
        "streams": "3,597,795",
        "youtubeID": "xLKvBwn_ias"
    },
    {
        "ranking": "9",
        "title": "KUSURA BAKMA",
        "artist": null,
        "image": "https://yt3.googleusercontent.com/s1cip4pQ1gjfUY62IdMmF7rrLYptdsx2y3d5DztuRDXCvqqMaVlAsAm5pu5rjDDzaK-FCzr8n8cNSGdI=w180-h180-l90-rj",
        "prev": "9",
        "streak": "25",
        "streams": "3,552,544",
        "youtubeID": "Y9AXKgqGwN4"
    },
    {
        "ranking": "10",
        "title": "Seni Düşündüm",
        "artist": null,
        "image": "https://yt3.googleusercontent.com/nVx5EpEAccZfwnoKATg0UH68OLDyZ23c70lsnSMqha1CfY9xwtX8u2JEVGleFXBqo7NQ7tpC4maI77XK=w180-h180-l90-rj",
        "prev": "8",
        "streak": "43",
        "streams": "3,420,433",
        "youtubeID": "3OGl69sY9Ys"
    },
    {
        "ranking": "11",
        "title": "Ömrüm",
        "artist": null,
        "image": "https://i.ytimg.com/vi/791Qe2oF-eY/default.jpg",
        "prev": "10",
        "streak": "9",
        "streams": "3,308,175",
        "youtubeID": "791Qe2oF-eY"
    },
    {
        "ranking": "12",
        "title": "Amatör",
        "artist": null,
        "image": "https://yt3.googleusercontent.com/NwWI-QqLMDVu7JgAWSAHdYlPUMQoCRSxr8mTXN5oaf_gBOjMifgOFtVRfVbJcM0LqnOFVg12rlgUPCwxtQ=w180-h180-l90-rj",
        "prev": "14",
        "streak": "24",
        "streams": "2,994,992",
        "youtubeID": "JzH6uWBtC3I"
    },
    {
        "ranking": "13",
        "title": "git",
        "artist": null,
        "image": "https://yt3.googleusercontent.com/AL5GFortkI-ABJdefiwQvoginRCm1hydrZbnVuDkfIHncunCZCw94GNk63KBwH4wwAz-XpXEHeSkSoE=w180-h180-l90-rj",
        "prev": "15",
        "streak": "44",
        "streams": "2,885,373",
        "youtubeID": "JWLWczFtCag"
    },
    {
        "ranking": "14",
        "title": "napıyosun mesela ?",
        "artist": null,
        "image": "https://yt3.googleusercontent.com/AL5GFortkI-ABJdefiwQvoginRCm1hydrZbnVuDkfIHncunCZCw94GNk63KBwH4wwAz-XpXEHeSkSoE=w180-h180-l90-rj",
        "prev": "13",
        "streak": "44",
        "streams": "2,749,503",
        "youtubeID": "_JfRAe4fbEE"
    },
    {
        "ranking": "15",
        "title": "Aşka Yürek Gerek",
        "artist": null,
        "image": "https://yt3.googleusercontent.com/xAnL_OA_Q_FrSJt7I3vD4BH68Sp24ovuEgCp_biLkqYxuhBVv8GUt3eVX49CZd_Q56fa2DaxQR49y7xC=w180-h180-l90-rj",
        "prev": "39",
        "streak": "53",
        "streams": "2,675,994",
        "youtubeID": "fuOgPU10THA"
    },
    {
        "ranking": "16",
        "title": "Vur Beni",
        "artist": null,
        "image": "https://yt3.googleusercontent.com/0lQf845Uymhoy3DJw7SUH5zH-UhxOpESq18ueu3X6syMhf1skX-Ep1U3KDxO_wSSjTbNLlUj2Ak961Y=w180-h180-l90-rj",
        "prev": "12",
        "streak": "4",
        "streams": "2,671,835",
        "youtubeID": "Dncs42FOBy8"
    },
    {
        "ranking": "17",
        "title": "Başrol Sensin (1. Yıl Özel)",
        "artist": null,
        "image": "https://yt3.googleusercontent.com/tPfAY3eh3ce6QKVhu7ADKAK3CCVktSjmaaAwV2-2LGFlUEsWcI9xMflJbavptYaWQlOuqXUE1ESaZjU=w180-h180-l90-rj",
        "prev": "20",
        "streak": "14",
        "streams": "2,594,460",
        "youtubeID": "ICfGdpZCE1Q"
    },
    {
        "ranking": "18",
        "title": "Üzülmedim Ki",
        "artist": null,
        "image": "https://yt3.googleusercontent.com/w57qpNUCpOz1ezR5RjkPTz0Tk9_E7HVT4NlqSmvp0H5Z2yi6GBcwtoQlwSaeum_TJUOBxAKe5KkRf455=w180-h180-l90-rj",
        "prev": "11",
        "streak": "9",
        "streams": "2,590,846",
        "youtubeID": "cahWIOCm5YM"
    },
    {
        "ranking": "19",
        "title": "Gül Ki Güller Açsın Al Yanağında | Anatolian Cover",
        "artist": null,
        "image": "https://i.ytimg.com/vi/EdfS1BPwX80/default.jpg",
        "prev": "-",
        "streak": "1",
        "streams": "2,576,347",
        "youtubeID": "EdfS1BPwX80"
    },
    {
        "ranking": "20",
        "title": "Kalpsiz Bir Serseri (Live)",
        "artist": null,
        "image": "https://yt3.googleusercontent.com/pw_YSGni45wY_nimeMZH2xuUL18XSYsdtouLdWCuvuk1SQmott7sQUpANjBIZG2-U8Tm1rtu8VrijDYz=w180-h180-l90-rj",
        "prev": "17",
        "streak": "13",
        "streams": "2,508,204",
        "youtubeID": "i9OqUDR-Y9g"
    },
    {
        "ranking": "21",
        "title": "Yerinde Dur",
        "artist": null,
        "image": "https://yt3.googleusercontent.com/h_g3sjwvofyrUWrI55KLfTaNSwGKpwARKnF7-QZBgnwItXbK6RXa52KkIiudoP7acA9bMfW23no8julQ=w180-h180-l90-rj",
        "prev": "19",
        "streak": "47",
        "streams": "2,496,016",
        "youtubeID": "_NoTqg152B0"
    },
    {
        "ranking": "22",
        "title": "COOOK PARDON",
        "artist": null,
        "image": "https://yt3.googleusercontent.com/5Z5EDDBu-SwAf19_YTKdXe0lNYsH6jS4fODvAcCZzSaOfaHCRqQQY_6rZDa-AvWkUVOiKWJmu5hAt4M=w180-h180-l90-rj",
        "prev": "18",
        "streak": "35",
        "streams": "2,480,241",
        "youtubeID": "wGAH8PSk-rg"
    },
    {
        "ranking": "23",
        "title": "Heyecan",
        "artist": null,
        "image": "https://yt3.googleusercontent.com/5Vz9JyCF39AQEgbV2Ko5MIjl3LESOT7RrR8jIBl28dRtsbOkca5iCDZDFkkQQ6bOhbZ29WKnWYlyb4Vd=w180-h180-l90-rj",
        "prev": "-",
        "streak": "54",
        "streams": "2,417,378",
        "youtubeID": "GR6r-jIryH0"
    },
    {
        "ranking": "24",
        "title": "Yemin Olsun",
        "artist": null,
        "image": "https://yt3.googleusercontent.com/aCWvGPSRc0elyDLWYPMmkv1LcIJbRDfQcdhLoEY1q1WZsiroT_WsHmGRScghFpg2D5nHMwe4Gd4_JZt1mQ=w180-h180-l90-rj",
        "prev": "21",
        "streak": "14",
        "streams": "2,191,523",
        "youtubeID": "2kW98NsS2_A"
    },
    {
        "ranking": "25",
        "title": "Sana Rağmen",
        "artist": null,
        "image": "https://i.ytimg.com/vi/5_lAs3qj1LU/default.jpg",
        "prev": "16",
        "streak": "13",
        "streams": "2,171,650",
        "youtubeID": "5_lAs3qj1LU"
    },
    {
        "ranking": "26",
        "title": "Snap",
        "artist": null,
        "image": "https://yt3.googleusercontent.com/5fw8JFZB87i4HnvIlpqkvMygbG5FfCaUyCZqlHsgn_IxrReYlr-vzJOup5L5qjhuC9k_06w8tyJnymsm=w180-h180-l90-rj",
        "prev": "33",
        "streak": "50",
        "streams": "2,167,000",
        "youtubeID": "jVQNc2XfCPk"
    },
    {
        "ranking": "27",
        "title": "Ayay",
        "artist": null,
        "image": "https://yt3.googleusercontent.com/z9ByacKDQAgI9EDrj3KY-h3eHXAkUToXUiID88mSmUZWgXgXKe2RNgb2X1VP_c7KbOyo-aqkPP5JOp7B=w180-h180-l90-rj",
        "prev": "28",
        "streak": "14",
        "streams": "2,151,739",
        "youtubeID": "MMLzq0Bh6XE"
    },
    {
        "ranking": "28",
        "title": "Heba Olan Dünler (feat. Berrin Keskin)",
        "artist": null,
        "image": "https://yt3.googleusercontent.com/_DzyiDlqIvxrp3hljOUf6kXKehXG4xxmgeTF9tTj8laX9vnPxDUxaWg0whHdcFvIXRIoJrJOb1OyF5TqzA=w180-h180-l90-rj",
        "prev": "24",
        "streak": "26",
        "streams": "2,066,031",
        "youtubeID": "WMPUyvqkJmo"
    },
    {
        "ranking": "29",
        "title": "Bir Çift Göz",
        "artist": null,
        "image": "https://yt3.googleusercontent.com/cWhjI80v3qaDBicPoH6tNghnI_FFCKv2cG7_My98wqnAcU-tpzG58qzm1bM5y9D0Hft74m47YHDIDmWo=w180-h180-l90-rj",
        "prev": "25",
        "streak": "47",
        "streams": "2,001,130",
        "youtubeID": "qDxfNmR95dM"
    },
    {
        "ranking": "30",
        "title": "Yeraltı",
        "artist": null,
        "image": "https://yt3.googleusercontent.com/xUl_PcQaVxYYNcI-NpfXWrY8IYiaDUWKOKiVux0XT7elT9UUZgcG2svY0Yb4hnsrSVr6_jAO9nnjCofN=w180-h180-l90-rj",
        "prev": "22",
        "streak": "16",
        "streams": "1,970,524",
        "youtubeID": "lweuCN4ASlY"
    },
    {
        "ranking": "31",
        "title": "Saygımdan",
        "artist": null,
        "image": "https://yt3.googleusercontent.com/8JjtRjtKPZpan78AFTLoVTrr7BkHBM7z0VyJnBNy8gXHvcxnEvqmmgWOrFX7ccTFlPjJSio25ZlrbO0=w180-h180-l90-rj",
        "prev": "32",
        "streak": "44",
        "streams": "1,969,670",
        "youtubeID": "4goQBlcdVUk"
    },
    {
        "ranking": "32",
        "title": "Bir Güldün",
        "artist": null,
        "image": "https://yt3.googleusercontent.com/Cxe24jcXzBQyqE3V55QkNPZAjn_b8-4Vviq5ZvxKlwhvTB0HpnWPRTWNEYG4xLRKz77FA9TytndW8_RW=w180-h180-l90-rj",
        "prev": "27",
        "streak": "21",
        "streams": "1,934,776",
        "youtubeID": "bnZoviZwjSc"
    },
    {
        "ranking": "33",
        "title": "Yangın Yeri",
        "artist": null,
        "image": "https://yt3.googleusercontent.com/2U2Uxa4Qs-FHaelgw3V0P2Ank_B-B-nC7w2OahYYx3MFcHM9givR_6Ql933HuK6mVePxVXMIaVq87bR8=w180-h180-l90-rj",
        "prev": "44",
        "streak": "2",
        "streams": "1,922,655",
        "youtubeID": "WgoVgSOuReY"
    },
    {
        "ranking": "34",
        "title": "Senden Insaf Diler Yarın",
        "artist": null,
        "image": "https://i.ytimg.com/vi/QJamrIqDTbw/default.jpg",
        "prev": "29",
        "streak": "45",
        "streams": "1,821,404",
        "youtubeID": "QJamrIqDTbw"
    },
    {
        "ranking": "35",
        "title": "Yar Gözlerin Ağlar Gibi",
        "artist": null,
        "image": "https://yt3.googleusercontent.com/6EDGGM-OQtoqUlh0gZJxOaXHJDSt8GYyC6gGHvY4f9mBrmQ1neaG9gX0n1N6m9lS46er58g3HEyA4Zw=w180-h180-l90-rj",
        "prev": "75",
        "streak": "2",
        "streams": "1,770,174",
        "youtubeID": "wwrbRhtNX9I"
    },
    {
        "ranking": "36",
        "title": "hay Allah",
        "artist": null,
        "image": "https://i.ytimg.com/vi/Lp7JKbTKx6M/default.jpg",
        "prev": "36",
        "streak": "14",
        "streams": "1,720,832",
        "youtubeID": "Lp7JKbTKx6M"
    },
    {
        "ranking": "37",
        "title": "Gel",
        "artist": null,
        "image": "https://yt3.googleusercontent.com/-klZBMa4CCiomS-CcPRw_2nsoP3T9c_wgG7SXaMq1e9l58mxAmR4X9r26kcWyTbWBPEn1XMEFdu6ruQk=w180-h180-l90-rj",
        "prev": "43",
        "streak": "24",
        "streams": "1,711,946",
        "youtubeID": "y5A2NmlFbOY"
    },
    {
        "ranking": "38",
        "title": "UYUYAMADIN DİMİ?",
        "artist": null,
        "image": "https://yt3.googleusercontent.com/wkdcJPVE6DPQ1Ks-s9kTCqrNMSs-uF3yjSfTzr2x1x_xVX3n-Ehce5ImpDrwFUcYbqWv4n1JiO2_RG-6=w180-h180-l90-rj",
        "prev": "30",
        "streak": "5",
        "streams": "1,671,425",
        "youtubeID": "eG79aUWKkKo"
    },
    {
        "ranking": "39",
        "title": "KTS",
        "artist": null,
        "image": "https://yt3.googleusercontent.com/5fw8JFZB87i4HnvIlpqkvMygbG5FfCaUyCZqlHsgn_IxrReYlr-vzJOup5L5qjhuC9k_06w8tyJnymsm=w180-h180-l90-rj",
        "prev": "47",
        "streak": "25",
        "streams": "1,647,591",
        "youtubeID": "yRqJ6gbkBA0"
    },
    {
        "ranking": "40",
        "title": "Sende Kalmış",
        "artist": null,
        "image": "https://yt3.googleusercontent.com/0lQf845Uymhoy3DJw7SUH5zH-UhxOpESq18ueu3X6syMhf1skX-Ep1U3KDxO_wSSjTbNLlUj2Ak961Y=w180-h180-l90-rj",
        "prev": "34",
        "streak": "4",
        "streams": "1,641,448",
        "youtubeID": "CRxxy29b06M"
    },
    {
        "ranking": "41",
        "title": "Kan Çiçekleri",
        "artist": null,
        "image": "https://i.ytimg.com/vi/utbTpJe04ec/default.jpg",
        "prev": "37",
        "streak": "14",
        "streams": "1,610,215",
        "youtubeID": "utbTpJe04ec"
    },
    {
        "ranking": "42",
        "title": "Zamansızdık",
        "artist": null,
        "image": "https://yt3.googleusercontent.com/5fw8JFZB87i4HnvIlpqkvMygbG5FfCaUyCZqlHsgn_IxrReYlr-vzJOup5L5qjhuC9k_06w8tyJnymsm=w180-h180-l90-rj",
        "prev": "52",
        "streak": "35",
        "streams": "1,557,655",
        "youtubeID": "TWo7ktEPxSg"
    },
    {
        "ranking": "43",
        "title": "YUH!",
        "artist": null,
        "image": "https://yt3.googleusercontent.com/oBvJl4LFYrWEo9S04tXnfIxWI-AbUkp-ZjtlOUndTXIxFXVSdA0PoO_dIYuN8yPKf1Bg8CV-y-n1EZOl=w180-h180-l90-rj",
        "prev": "-",
        "streak": "1",
        "streams": "1,553,272",
        "youtubeID": "Ixp80E2DjhE"
    },
    {
        "ranking": "44",
        "title": "Beni Al (Live)",
        "artist": null,
        "image": "https://i.ytimg.com/vi/3U7_DxeX8mk/default.jpg",
        "prev": "31",
        "streak": "11",
        "streams": "1,549,187",
        "youtubeID": "3U7_DxeX8mk"
    },
    {
        "ranking": "45",
        "title": "Rüya Gibiydin",
        "artist": null,
        "image": "https://yt3.googleusercontent.com/NzyiE2v5hORQaT_LUx1b69Esdg0pDyiV7XfLJhH1cs4UAY3GUm6qOAkhSEese1bS8JpCBGv_BK5IxA=w180-h180-l90-rj",
        "prev": "35",
        "streak": "8",
        "streams": "1,536,854",
        "youtubeID": "sNZW_GxwSu0"
    },
    {
        "ranking": "46",
        "title": "Ama Başaramadım",
        "artist": null,
        "image": "https://yt3.googleusercontent.com/NRrpvelJJRWZEiqiW-zj06N4EhXcm5svBcMxeY0tCkEw4Pk0DRLmNcn8VJQvjg1A__-4oMcCUtUzQo6NSg=w180-h180-l90-rj",
        "prev": "51",
        "streak": "17",
        "streams": "1,517,748",
        "youtubeID": "m-gADGCCLmw"
    },
    {
        "ranking": "47",
        "title": "Beyaz Olamadım Ama Karada Değilim",
        "artist": null,
        "image": "https://i.ytimg.com/vi/W9nJmQxS6Hk/default.jpg",
        "prev": "-",
        "streak": "1",
        "streams": "1,514,514",
        "youtubeID": "W9nJmQxS6Hk"
    },
    {
        "ranking": "48",
        "title": "Ey Aşk",
        "artist": null,
        "image": "https://yt3.googleusercontent.com/pLXyuYu3FgFwgD2rX1eApSyLqjwhOOUjzq2wVGXfGitnVJSqUDZgQLdMkcccLnjNfsSGZVDMC25vtOiD=w180-h180-l90-rj",
        "prev": "38",
        "streak": "47",
        "streams": "1,475,911",
        "youtubeID": "rYJjgfCfBOU"
    },
    {
        "ranking": "49",
        "title": "Sakla (Erhan Boraer Remix)",
        "artist": null,
        "image": "https://yt3.googleusercontent.com/aE1Fs-OYYQBcEQHDNKhj5DQff70Cq9FpGqjA2u1NCgFZxsn2KYazsdto-hddzbfmtT3_JXPx49e6ogWIdg=w180-h180-l90-rj",
        "prev": "59",
        "streak": "3",
        "streams": "1,456,113",
        "youtubeID": "YPpTsgXfTzA"
    },
    {
        "ranking": "50",
        "title": "DELİ OLMİŞUM DELİ",
        "artist": null,
        "image": "https://yt3.googleusercontent.com/vhoIPdvc671N00M4oY8VSdyvbZ1NauIQph0of-J0WZnwlJ1gKvVWztVApvBZF4xQXVTrPL4_3D5PJ6IX=w180-h180-l90-rj",
        "prev": "41",
        "streak": "13",
        "streams": "1,454,358",
        "youtubeID": "ac-nJlba6yc"
    },
    {
        "ranking": "51",
        "title": "RÜYA",
        "artist": null,
        "image": "https://yt3.googleusercontent.com/fLPOovxD838iNJNOb8ezp19QF1RyyDal5juElBQIOkjVeWaXOG2bm_MeFDR0PY-iFEN_7ALJI8LZiuw=w180-h180-l90-rj",
        "prev": "-",
        "streak": "23",
        "streams": "1,408,611",
        "youtubeID": "nB0Kdt_QQ-w"
    },
    {
        "ranking": "52",
        "title": "NALAKA",
        "artist": null,
        "image": "https://yt3.googleusercontent.com/pfSL4IZI5gJN1DHwgPhhdhT7Z_W9ITIZAsyTZyuJAdjq_kErsd1W4js2tisffWnpooenGDWnNmhmsl-P=w180-h180-l90-rj",
        "prev": "40",
        "streak": "6",
        "streams": "1,375,045",
        "youtubeID": "2bOPA8nNAR4"
    },
    {
        "ranking": "53",
        "title": "Cilvelim",
        "artist": null,
        "image": "https://yt3.googleusercontent.com/52XQjNVya5V2X36YtCwwzsya0NuGkTrxsPhm-iwAH3wpgfwLpcX9CJXWVGtuquYB7-YpJaExee9MuL8SVw=w180-h180-l90-rj",
        "prev": "45",
        "streak": "11",
        "streams": "1,346,243",
        "youtubeID": "SuqkqV0wRHs"
    },
    {
        "ranking": "54",
        "title": "RDM",
        "artist": null,
        "image": "https://yt3.googleusercontent.com/fZxR6mxODlKH9hH0cBMfhGGj3TzG4IT1jkIwh4zd5aCNzbYgCEirVqU0foeJvp6070Mfbe3bT6bq0IIhZw=w180-h180-l90-rj",
        "prev": "48",
        "streak": "4",
        "streams": "1,338,547",
        "youtubeID": "niwyc2zZI-c"
    },
    {
        "ranking": "55",
        "title": "Manifest",
        "artist": null,
        "image": "https://yt3.googleusercontent.com/5fw8JFZB87i4HnvIlpqkvMygbG5FfCaUyCZqlHsgn_IxrReYlr-vzJOup5L5qjhuC9k_06w8tyJnymsm=w180-h180-l90-rj",
        "prev": "-",
        "streak": "23",
        "streams": "1,323,548",
        "youtubeID": "fbelrTRlls8"
    },
    {
        "ranking": "56",
        "title": "Sorma",
        "artist": null,
        "image": "https://i.ytimg.com/vi/k_S10l_4nMc/default.jpg",
        "prev": "68",
        "streak": "6",
        "streams": "1,286,883",
        "youtubeID": "k_S10l_4nMc"
    },
    {
        "ranking": "57",
        "title": "Burda Geceler",
        "artist": null,
        "image": "https://yt3.googleusercontent.com/9bhvWwSCtZhwAhP1okiKrnHozXtL4Q3xEnTn0JgE6K8pLDZpBS3tKTUEfUtDf9_DH7svx9WWVikmV8u8=w180-h180-l90-rj",
        "prev": "60",
        "streak": "3",
        "streams": "1,270,781",
        "youtubeID": "A0vNazJ-lfI"
    },
    {
        "ranking": "58",
        "title": "Geliyorsun Aklıma",
        "artist": null,
        "image": "https://yt3.googleusercontent.com/CYxFPcCLIhjMXB9v8znPYHetgv5DsXgqedqGrdxOHk_uZviBFK7qVKwV2hvGNyb0kVJFsMog17YoNK4=w180-h180-l90-rj",
        "prev": "-",
        "streak": "1",
        "streams": "1,267,505",
        "youtubeID": "mrqSrPhOZSY"
    },
    {
        "ranking": "59",
        "title": "Arıyo",
        "artist": null,
        "image": "https://yt3.googleusercontent.com/5fw8JFZB87i4HnvIlpqkvMygbG5FfCaUyCZqlHsgn_IxrReYlr-vzJOup5L5qjhuC9k_06w8tyJnymsm=w180-h180-l90-rj",
        "prev": "71",
        "streak": "24",
        "streams": "1,252,473",
        "youtubeID": "yQ9lXHfv9Yg"
    },
    {
        "ranking": "60",
        "title": "İki Tas Çorba",
        "artist": null,
        "image": "https://i.ytimg.com/vi/ESprxDaAtKQ/default.jpg",
        "prev": "-",
        "streak": "1",
        "streams": "1,247,925",
        "youtubeID": "ESprxDaAtKQ"
    },
    {
        "ranking": "61",
        "title": "Doğru sandıklarım meğer hep yalanlar",
        "artist": null,
        "image": "https://i.ytimg.com/vi/6PpvkEzTczw/default.jpg",
        "prev": "100",
        "streak": "2",
        "streams": "1,240,441",
        "youtubeID": "6PpvkEzTczw"
    },
    {
        "ranking": "62",
        "title": "Hermès 2.0",
        "artist": null,
        "image": "https://i.ytimg.com/vi/9OuvUfaQJ-c/default.jpg",
        "prev": "53",
        "streak": "11",
        "streams": "1,228,535",
        "youtubeID": "9OuvUfaQJ-c"
    },
    {
        "ranking": "63",
        "title": "Misafir",
        "artist": null,
        "image": "https://i.ytimg.com/vi/t0W1Xp0xJgA/default.jpg",
        "prev": "54",
        "streak": "7",
        "streams": "1,209,738",
        "youtubeID": "t0W1Xp0xJgA"
    },
    {
        "ranking": "64",
        "title": "Gel dedim geldin",
        "artist": null,
        "image": "https://yt3.googleusercontent.com/eoniiBxwfIbdfyMT9x7wxzUl-8cxPbWchyUbkx8XeMxXrEkmyPoERhMC-PUHUbO8JP6AY-cbW1lKucou=w180-h180-l90-rj",
        "prev": "62",
        "streak": "2",
        "streams": "1,143,100",
        "youtubeID": "qcfS7amxPYA"
    },
    {
        "ranking": "65",
        "title": "Edalı da Modalı Yar",
        "artist": null,
        "image": "https://i.ytimg.com/vi/Vc43CTzrr1Q/default.jpg",
        "prev": "69",
        "streak": "9",
        "streams": "1,108,762",
        "youtubeID": "Vc43CTzrr1Q"
    },
    {
        "ranking": "66",
        "title": "Şıkır Şıkır",
        "artist": null,
        "image": "https://i.ytimg.com/vi/2jw6ZqoJAX8/default.jpg",
        "prev": "76",
        "streak": "23",
        "streams": "1,102,983",
        "youtubeID": "2jw6ZqoJAX8"
    },
    {
        "ranking": "67",
        "title": "Sebepsiz Ayrılık",
        "artist": null,
        "image": "https://yt3.googleusercontent.com/0lQf845Uymhoy3DJw7SUH5zH-UhxOpESq18ueu3X6syMhf1skX-Ep1U3KDxO_wSSjTbNLlUj2Ak961Y=w180-h180-l90-rj",
        "prev": "49",
        "streak": "4",
        "streams": "1,100,247",
        "youtubeID": "M-8V86jSrrY"
    },
    {
        "ranking": "68",
        "title": "Bir Dünyasın",
        "artist": null,
        "image": "https://yt3.googleusercontent.com/hZfl97uNDw3-V5Fd0Ql92y7YcWZcCk0uzcwFkaemN3fmh3lYn_LWgkEjDQeDuUvqT95bk5XEB23o_1PyBA=w180-h180-l90-rj",
        "prev": "67",
        "streak": "19",
        "streams": "1,099,369",
        "youtubeID": "2j9XfINfvJQ"
    },
    {
        "ranking": "69",
        "title": "Kutupta Yaz Gibi",
        "artist": null,
        "image": "https://yt3.googleusercontent.com/0lQf845Uymhoy3DJw7SUH5zH-UhxOpESq18ueu3X6syMhf1skX-Ep1U3KDxO_wSSjTbNLlUj2Ak961Y=w180-h180-l90-rj",
        "prev": "58",
        "streak": "4",
        "streams": "1,081,542",
        "youtubeID": "WyYegiLFsJE"
    },
    {
        "ranking": "70",
        "title": "Güm Güm (Remix) (feat. Onurr)",
        "artist": null,
        "image": "https://yt3.googleusercontent.com/esC6bOqseRAq4hyHBPKKEDgCKfX-E8yNLrf5l5_eraKdneYN1KNVaS6FbO6gmDPk6pbvisq0_H63KpEPIg=w180-h180-l90-rj",
        "prev": "61",
        "streak": "6",
        "streams": "1,081,322",
        "youtubeID": "xbr5sV68laE"
    },
    {
        "ranking": "71",
        "title": "Ne Sevdalar Yaşadım",
        "artist": null,
        "image": "https://yt3.googleusercontent.com/q9QycgJEHM0iz05q-f1j7bO0_-y_STPBZeGalxJfaRWxwM-1fHzLGpCR8ZzM7C6HTvBagXHxRUmTIQw=w180-h180-l90-rj",
        "prev": "88",
        "streak": "5",
        "streams": "1,081,047",
        "youtubeID": "Ga0TS6yjzuE"
    },
    {
        "ranking": "72",
        "title": "Yüzük",
        "artist": null,
        "image": "https://yt3.googleusercontent.com/mGmAY3B2Nb2bvYAVfu59rHTqdHYBzPQA7X-FLM0Z6qX5iLrRUAeUgh8X76n3WMuKGa5zLndknrgZHPoCRg=w180-h180-l90-rj",
        "prev": "85",
        "streak": "3",
        "streams": "1,066,790",
        "youtubeID": "srmocZuoxU8"
    },
    {
        "ranking": "73",
        "title": "NASİL SEVDUM",
        "artist": null,
        "image": "https://i.ytimg.com/vi/k4xwt0374rU/default.jpg",
        "prev": "63",
        "streak": "11",
        "streams": "1,066,387",
        "youtubeID": "k4xwt0374rU"
    },
    {
        "ranking": "74",
        "title": "Yaşanacaksa",
        "artist": null,
        "image": "https://yt3.googleusercontent.com/5fw8JFZB87i4HnvIlpqkvMygbG5FfCaUyCZqlHsgn_IxrReYlr-vzJOup5L5qjhuC9k_06w8tyJnymsm=w180-h180-l90-rj",
        "prev": "97",
        "streak": "22",
        "streams": "1,036,083",
        "youtubeID": "zuP6l1oA3Ro"
    },
    {
        "ranking": "75",
        "title": "Bana Bakmayın",
        "artist": null,
        "image": "https://yt3.googleusercontent.com/LaFLYAvk3QzB42nzgqZmyUfK1wI5uPMAMVCoecAkVZS6MhzzeZs_MOm-Tiiwp2BlztcoQqfXAxHxDwU4=w180-h180-l90-rj",
        "prev": "91",
        "streak": "6",
        "streams": "1,035,161",
        "youtubeID": "8jK5Z4wBbUc"
    },
    {
        "ranking": "76",
        "title": "57 (feat. Bakan)",
        "artist": null,
        "image": "https://yt3.googleusercontent.com/UgK5lauMbNgM5X-skk3R5jJP-cTojG3IOLRPFry17IwQOey2D0-wN8QrgcV2eRAD3bXGXylkdbEY59r4=w180-h180-l90-rj",
        "prev": "65",
        "streak": "3",
        "streams": "1,033,607",
        "youtubeID": "w9uHnR0Iozw"
    },
    {
        "ranking": "77",
        "title": "Kumralım",
        "artist": null,
        "image": "https://i.ytimg.com/vi/UXK9s54VmxQ/default.jpg",
        "prev": "-",
        "streak": "33",
        "streams": "1,004,382",
        "youtubeID": "UXK9s54VmxQ"
    },
    {
        "ranking": "78",
        "title": "HANİ",
        "artist": null,
        "image": "https://yt3.googleusercontent.com/TiBMCvU2k9JkNfx6TASee2rQeI6z3h1d9S6_gE-lIDVd0iGa1NfXpQuDfAmurTNSaRNk07DjpTEQ2mor=w180-h180-l90-rj",
        "prev": "66",
        "streak": "7",
        "streams": "990,849",
        "youtubeID": "aPFeLf3qZ3M"
    },
    {
        "ranking": "79",
        "title": "Deli Zaman",
        "artist": null,
        "image": "https://i.ytimg.com/vi/oCvVwBEfB8Y/default.jpg",
        "prev": "55",
        "streak": "5",
        "streams": "975,843",
        "youtubeID": "oCvVwBEfB8Y"
    },
    {
        "ranking": "80",
        "title": "Zeytin Yaprağı Yeşil",
        "artist": null,
        "image": "https://i.ytimg.com/vi/hMed1jPgrmY/default.jpg",
        "prev": "80",
        "streak": "9",
        "streams": "966,561",
        "youtubeID": "hMed1jPgrmY"
    },
    {
        "ranking": "81",
        "title": "yenildiğim tek savaştın",
        "artist": null,
        "image": "https://i.ytimg.com/vi/K2-QZ-hEU9Y/default.jpg",
        "prev": "73",
        "streak": "11",
        "streams": "960,623",
        "youtubeID": "K2-QZ-hEU9Y"
    },
    {
        "ranking": "82",
        "title": "Dertsiz İnsan Yok Dayi",
        "artist": null,
        "image": "https://yt3.googleusercontent.com/LqeI6Iw2IHt6eJjOnQBAX4k9a0J1G_3Yt5TDn2Ee0wumgT6wRX5_qxImyRQJ71gsC3hchArC99YIyWDS=w180-h180-l90-rj",
        "prev": "93",
        "streak": "2",
        "streams": "957,468",
        "youtubeID": "Pt-TPo05fdI"
    },
    {
        "ranking": "83",
        "title": "Yok Yok",
        "artist": null,
        "image": "https://i.ytimg.com/vi/sDIgd_qz764/default.jpg",
        "prev": "70",
        "streak": "5",
        "streams": "954,754",
        "youtubeID": "sDIgd_qz764"
    },
    {
        "ranking": "84",
        "title": "Yakar Geçerim",
        "artist": null,
        "image": "https://yt3.googleusercontent.com/Egk85-UzSC6k49X1zNM61SceavtCPHpNDpYxFslp_V0XF7MeniAX6An0kinvZTThs0Li6I92nuR2lpqHdw=w180-h180-l90-rj",
        "prev": "86",
        "streak": "31",
        "streams": "953,672",
        "youtubeID": "Xpp_y2Os5Co"
    },
    {
        "ranking": "85",
        "title": "vODKA BELUGA",
        "artist": null,
        "image": "https://i.ytimg.com/vi/-j8xjPyQlws/default.jpg",
        "prev": "99",
        "streak": "16",
        "streams": "951,075",
        "youtubeID": "-j8xjPyQlws"
    },
    {
        "ranking": "86",
        "title": "En Derine",
        "artist": null,
        "image": "https://yt3.googleusercontent.com/CxKFmpTJs7pmalv-9N_uVOuEnZpg6277JT639jK3wTpiT-uS4-xQd9P_1qZ0spEjOPj1K6OacQuUxxiL=w180-h180-l90-rj",
        "prev": "74",
        "streak": "13",
        "streams": "925,709",
        "youtubeID": "hj8qM6h3S1s"
    },
    {
        "ranking": "87",
        "title": "Ara Beni Lütfen",
        "artist": null,
        "image": "https://yt3.googleusercontent.com/U__Z3Lqe6GIIum8RLrqf9Ls5tus8-UOhEryimPhvhYWR5MvUvLHRycLI-TI6KG4ulo65h53hoyLUu3Y=w180-h180-l90-rj",
        "prev": "90",
        "streak": "7",
        "streams": "877,013",
        "youtubeID": "BoB3_vFm7bM"
    },
    {
        "ranking": "88",
        "title": "İsyankar (Live) (feat. Mert Demir)",
        "artist": null,
        "image": "https://i.ytimg.com/vi/zKfZgDbYuDo/default.jpg",
        "prev": "96",
        "streak": "26",
        "streams": "873,292",
        "youtubeID": "zKfZgDbYuDo"
    },
    {
        "ranking": "89",
        "title": "Kurşun Adres Sormaz Ki (Live)",
        "artist": null,
        "image": "https://i.ytimg.com/vi/IVJlNRMailw/default.jpg",
        "prev": "72",
        "streak": "15",
        "streams": "862,844",
        "youtubeID": "IVJlNRMailw"
    },
    {
        "ranking": "90",
        "title": "Çağır Beni Gelem Sana",
        "artist": null,
        "image": "https://i.ytimg.com/vi/7PipmtZ7e6M/default.jpg",
        "prev": "84",
        "streak": "9",
        "streams": "856,297",
        "youtubeID": "7PipmtZ7e6M"
    },
    {
        "ranking": "91",
        "title": "ASLAN YAKIŞMAZ KAFESTE",
        "artist": null,
        "image": "https://yt3.googleusercontent.com/kO9X-L3sxc6s8hVQAjF8psu0DsUhmy5axMKjUcGI4vw7mLOOar_NTdS5IluZ2d3Jkh_8z4QdqkVoxKfMPA=w180-h180-l90-rj",
        "prev": "-",
        "streak": "5",
        "streams": "855,386",
        "youtubeID": "Ba_5P6G79do"
    },
    {
        "ranking": "92",
        "title": "Ciğerparem",
        "artist": null,
        "image": "https://i.ytimg.com/vi/fSL-tTu_HQQ/default.jpg",
        "prev": "77",
        "streak": "4",
        "streams": "855,217",
        "youtubeID": "fSL-tTu_HQQ"
    },
    {
        "ranking": "93",
        "title": "Halef Selef",
        "artist": null,
        "image": "https://yt3.googleusercontent.com/55_R83c9GfPZ1WXITMsQQrEaQ0QLNS5tNqRa-Oms3O5yxKBO_E8UQTdTf1-ZwkkUCmLs_yzyo1krWcEOwA=w180-h180-l90-rj",
        "prev": "94",
        "streak": "13",
        "streams": "846,888",
        "youtubeID": "Vxm666Lk1ms"
    },
    {
        "ranking": "94",
        "title": "YIN YANG",
        "artist": null,
        "image": "https://yt3.googleusercontent.com/-rvAgNKft-euVNIfEj1lfjHcZdz4Xg_fACIb9IRvw0KhwzcizJ5AkzILs7g6xKL91gCQ96oeut9BEbw=w180-h180-l90-rj",
        "prev": "95",
        "streak": "12",
        "streams": "843,728",
        "youtubeID": "lDpXhLzJQsA"
    },
    {
        "ranking": "95",
        "title": "9mm",
        "artist": null,
        "image": "https://yt3.googleusercontent.com/gs8CeAA-oxLLjQmaKdnJp-XzJ5n6BYdaijspPa2f8tv7aSQRGWTP_ujkCGr6csSM_QpW9KKGbcolroY=w180-h180-l90-rj",
        "prev": "-",
        "streak": "10",
        "streams": "833,173",
        "youtubeID": "mVjmSBBbY2o"
    },
    {
        "ranking": "96",
        "title": "Bu Yüzden",
        "artist": null,
        "image": "https://yt3.googleusercontent.com/Ey2HOhgNNSuVdf6SL6NAVuGowMRIaCGhoG9PunlkdzEraVG9v4QSFyfXwn-xCJUPGvEj-erH6n9r79E=w180-h180-l90-rj",
        "prev": "-",
        "streak": "1",
        "streams": "831,929",
        "youtubeID": "OnCh5Df1ytw"
    },
    {
        "ranking": "97",
        "title": "Aynı Aşklar",
        "artist": null,
        "image": "https://yt3.googleusercontent.com/1jsrxR5xb8EtsbBHyU01KJY05YrvsE9CEpvdg596HKk9_3T1pOS7JBBoMYofNPBO-1XGFsrHtGkJz1F0=w180-h180-l90-rj",
        "prev": "79",
        "streak": "5",
        "streams": "827,223",
        "youtubeID": "Pb-9g5c8cAc"
    },
    {
        "ranking": "98",
        "title": "Bir Derdim Var",
        "artist": null,
        "image": "https://yt3.googleusercontent.com/YieeY2qGX5Sc7kwPdKTNej3RaCz2fqOG9Yi6VMnHHFw5BWFTM3xqwVKyS1mJZBqnsKJQ4-cIrvp6YmYk=w180-h180-l90-rj",
        "prev": "-",
        "streak": "59",
        "streams": "810,120",
        "youtubeID": "7RW8n4iXZbA"
    },
    {
        "ranking": "99",
        "title": "Gitmeyesin",
        "artist": null,
        "image": "https://yt3.googleusercontent.com/VY2SowRw7hqYBHM-Wx7VsTh_ixUp43osn3GoTnnYLLGcRUG_xbSUfcZa4HkhqGmWj4ZQqhevkGGkebE=w180-h180-l90-rj",
        "prev": "82",
        "streak": "11",
        "streams": "809,756",
        "youtubeID": "cAbQcPFTZW4"
    },
    {
        "ranking": "100",
        "title": "Bangır Bangır",
        "artist": null,
        "image": "https://yt3.googleusercontent.com/RHSpT6zzB89XPrYZqLxHeZd15wh05GEhECHEM6Grydpts8lytbhlp2vxcsYq2Z88HDWj5cb3aJK--Z0=w180-h180-l90-rj",
        "prev": "-",
        "streak": "37",
        "streams": "807,893",
        "youtubeID": "icZ-OlVSvb4"
    }
]